<job id="myJob" xmlns="http://xmlns.jcp.org/xml/ns/javaee" version="1.0">
    <step id="myStep" next="step2">
        <!-- Checkpoint is implicit for chunk items -->
        <chunk item-count="4">
            <reader ref="myItemReader"/>
            <processor ref="myItemProcessor"/>
            <writer ref="myItemWriter"/>
        </chunk>
    </step>
    <step id="step2">
        <batchlet ref="myBatchlet"/>
    </step>
    <listeners>
        <listener ref="infoJobListener"/>
    </listeners>
</job>

